spambind/__init__.py
spambind/errors.py
spambind/DIC/DICToolkit.cpython-312-x86_64-linux-gnu.so
spambind/DIC/src/DICToolkit.cpp
spambind/DIC/src/applyPhi.cpp
spambind/DIC/src/binning.cpp
spambind/DIC/src/computeDICoperators.cpp
spambind/DIC/src/computeGMresidualAndPhase.cpp
spambind/DIC/src/pixelSearchGC.cpp
spambind/filters/filtersToolkit.cpython-312-x86_64-linux-gnu.so
spambind/filters/src/filtersToolkit.cpp
spambind/filters/src/hessian.cpp
spambind/filters/src/movingFilters.cpp
spambind/kalisphera/kalispheraToolkit.cpython-312-x86_64-linux-gnu.so
spambind/kalisphera/src/kalisphera.cpp
spambind/kalisphera/src/kalispheraToolkit.cpp
spambind/label/labelToolkit.cpython-312-x86_64-linux-gnu.so
spambind/label/src/boundingBoxes.cpp
spambind/label/src/centresOfMass.cpp
spambind/label/src/checkPointInsideTetrahedron.cpp
spambind/label/src/labelContacts.cpp
spambind/label/src/labelToFloat.cpp
spambind/label/src/labelToolkit.cpp
spambind/label/src/momentOfInertia.cpp
spambind/label/src/relabel.cpp
spambind/label/src/setVoronoi.cpp
spambind/label/src/tetPixelLabel.cpp
spambind/label/src/volumes.cpp
spambind/measurements/measurementsToolkit.cpython-312-x86_64-linux-gnu.so
spambind/measurements/src/correlationFunction.cpp
spambind/measurements/src/curvatures.cpp
spambind/measurements/src/measurementsToolkit.cpp
spambind/measurements/src/porosityFieldBinary.cpp
spambind/mesh/meshToolkit.cpython-312-x86_64-linux-gnu.so
spambind/mesh/src/connectivityMatrix.cpp
spambind/mesh/src/crpacking.cpp
spambind/mesh/src/meshToolkit.cpp
spambind/mesh/src/projmorpho.cpp
spambind/mesh/src/tetrahedron.cpp
spambind-0.8.2.data/data/share/img/icon.png
spambind-0.8.2.data/data/share/img/spam-horizontal.png
spambind-0.8.2.data/data/share/img/spam-logo.png
spambind.libs/libgmp-afec2dd4.so.10.2.0
spambind.libs/libgomp-a34b3233.so.1.0.0
spambind-0.8.2.dist-info/METADATA
spambind-0.8.2.dist-info/WHEEL
spambind-0.8.2.dist-info/top_level.txt
spambind-0.8.2.dist-info/RECORD
spambind-0.8.2.dist-info/licenses/LICENSE.md
