Metadata-Version: 2.4
Name: spambind
Version: 0.8.2
Summary: Software for the Practical Analysis of Materials
Author-email: Edward Andò <edward.ando@epfl.ch>, Emmanuel Roubin <emmanuel.roubin@univ-grenoble-alpes.fr>, Gustavo Pinzón <gustavo.pinzon-forero@esrf.fr>, Olga Stamati <olga.stamati@univ-grenoble-alpes.fr>
Maintainer-email: Edward Andò <edward.ando@epfl.ch>, Emmanuel Roubin <emmanuel.roubin@univ-grenoble-alpes.fr>, Gustavo Pinzón <gustavo.pinzon-forero@esrf.fr>, Olga Stamati <olga.stamati@univ-grenoble-alpes.fr>
License-Expression: GPL-3.0-or-later
Project-URL: Homepage, https://spam-project.dev
Project-URL: Documentation, https://spam-project.dev/docs/
Project-URL: Repository, https://gitlab.com/spam-project/spam
Keywords: digital volume correlation,digital image correlation,registration,multimodal registration,strain calculation,label analysis,image analysis,random fields,synthetic images
Classifier: Development Status :: 4 - Beta
Classifier: Environment :: Console
Classifier: Intended Audience :: Science/Research
Classifier: Operating System :: POSIX :: Linux
Classifier: Programming Language :: Python :: 3
Classifier: Programming Language :: Python :: 3.9
Classifier: Programming Language :: Python :: 3.10
Classifier: Programming Language :: Python :: 3.11
Classifier: Programming Language :: Python :: 3.12
Classifier: Programming Language :: Python :: 3.13
Classifier: Programming Language :: Python :: 3 :: Only
Classifier: Topic :: Scientific/Engineering :: Image Recognition
Classifier: Topic :: Scientific/Engineering :: Mathematics
Requires-Python: >=3.9
License-File: LICENSE.md
Dynamic: license-file
